uuidentifier/__init__.py
uuidentifier/snowflake.py
uuidentifier-0.0.5.dist-info/METADATA
uuidentifier-0.0.5.dist-info/WHEEL
uuidentifier-0.0.5.dist-info/top_level.txt
uuidentifier-0.0.5.dist-info/RECORD
