Metadata-Version: 2.1
Name: uuidentifier
Version: 0.0.5
Summary: Universally Unique Identifier package
Home-page: https://github.com/private_repo/uuidentifier
Author: slipper
Author-email: r2fscg@gmail.com
License: UNKNOWN
Platform: UNKNOWN
Classifier: Programming Language :: Python :: 3
Classifier: License :: OSI Approved :: MIT License
Classifier: Operating System :: OS Independent
Requires-Dist: joblib
